pdf_template/__init__.py
pdf_template/__version__.py
pdf_template/pdftemplate.py
pdf_template/pypdftk.py
pdf_template-0.0.2.dist-info/METADATA
pdf_template-0.0.2.dist-info/WHEEL
pdf_template-0.0.2.dist-info/top_level.txt
pdf_template-0.0.2.dist-info/RECORD
