Metadata-Version: 2.1
Name: pdf-template
Version: 0.0.2
Summary: Library wrapping pdftk to fill and sign PDFs
Home-page: https://github.com/vote/pdf_template
Author: Ben Weissmann
Author-email: ben@voteamerica.com
Maintainer: Ben Weissmann
Maintainer-email: ben@voteamerica.com
License: BSD
Keywords: python pdf signature pdftk template
Platform: UNKNOWN
Classifier: Development Status :: 5 - Production/Stable
Classifier: License :: OSI Approved :: BSD License
Classifier: Intended Audience :: Developers
Classifier: Intended Audience :: System Administrators
Classifier: Operating System :: OS Independent
Classifier: Topic :: Text Editors :: Word Processors
Classifier: Programming Language :: Python :: 3.5
Classifier: Programming Language :: Python :: 3.6
Classifier: Programming Language :: Python :: 3.7
Classifier: Programming Language :: Python :: 3.8
Requires-Dist: Pillow
Requires-Dist: reportlab
Requires-Dist: dataclasses (>=0.6) ; python_version < "3.7"
